{
  "generator-angularjs-library": {
    "props": {
      "author": {
        "name": "Pedro Lucas Porcellis",
        "email": "pedrolucasporcellis@gmail.com"
      },
      "libraryName": {
        "original": "Atlas",
        "camelized": "atlas",
        "dasherized": "atlas",
        "slugified": "atlas",
        "parts": [
          "atlas"
        ]
      },
      "includeModuleDirectives": true,
      "includeModuleFilters": false,
      "includeModuleServices": true,
      "includeAngularModuleResource": false,
      "includeAngularModuleCookies": false,
      "includeAngularModuleSanitize": false,
      "librarySrcDirectory": "src/atlas",
      "libraryUnitTestDirectory": "test/unit/atlas",
      "libraryUnitE2eDirectory": "test/e2e/atlas"
    }
  }
}